{
  "environments": [
    {
    "id": "local",
    "label": "Local",
    "url": "http://localhost:4000/api/v1",
    "description": "Local environment",
    "service": {
      "formio": {
        "username": "me@lodev.xyz",
        "password": "secret"
      },
      "keycloak": {
        "tokenUrl": "http://keycloak.lodev.xyz/auth/realms/dev/protocol/openid-connect/token",
        "clientId": "service-account",
        "secret": "ed041195-fdf8-424b-a061-2081ea5067f1"
      }
    },
    "editable": true,
    "variable-replacements": [
      {
        "{$.environmentContext.referenceDataUrl}": "http://localhost:5000/v1/entities"
      },
      {
        "{$.staffDetailsContext.staffId}": "{{guid}}"
      },
      {
        "{$.keycloakContext.givenName}": "{{firstName}}"
      },
      {
        "{$.keycloakContext.familyName}": "{{lastName}}"
      },
      {
        "{$.someContext.id}" : 3
      }
    ]
  }, {
      "id": "dev",
      "label": "Dev",
      "url": "http://formapi.lodev.xyz/api/v1",
      "description": "Dev environment",
      "service": {
        "formio": {
          "username": "me@lodev.xyz",
          "password": "secret"
        },
        "keycloak": {
          "tokenUrl": "http://keycloak.lodev.xyz/auth/realms/dev/protocol/openid-connect/token",
          "clientId": "service-account",
          "secret": "ed041195-fdf8-424b-a061-2081ea5067f1"
        }
      },
      "editable": false,
      "variable-replacements": [
        {
          "{$.environmentContext.referenceDataUrl}": "http://localhost:5000/v1/entities"
        },
        {
          "{$.staffDetailsContext.staffId}": "{{guid}}"
        },
        {
          "{$.keycloakContext.givenName}": "{{firstName}}"
        },
        {
          "{$.keycloakContext.familyName}": "{{lastName}}"
        },
        {
          "{$.someContext.id}" : 3
        }
      ]
    }],
  "gov-uk-enabled" : true,
  "keycloak": {
    "authUrl": "http://keycloak.lodev.xyz/auth",
    "clientId": "platform-ui",
    "realm": "dev",
    "access-roles" : ["platform"],
    "promotion-roles" : ["platform"],
    "edit-roles" : ["platform"]
  }
}
